aylluiot/__init__.py
aylluiot/core.py
aylluiot/devices.py
aylluiot/aws/__init__.py
aylluiot/aws/service.py
aylluiot/aws/thing.py
aylluiot/utils/__init__.py
aylluiot/utils/data.py
aylluiot/utils/devices.py
aylluiot/utils/path.py
ayllu_iot-1.0.13.dist-info/LICENSE
ayllu_iot-1.0.13.dist-info/METADATA
ayllu_iot-1.0.13.dist-info/WHEEL
ayllu_iot-1.0.13.dist-info/top_level.txt
ayllu_iot-1.0.13.dist-info/RECORD
