Metadata-Version: 2.1
Name: ayllu-iot
Version: 1.0.13
Summary: Python Library to run IoT systems.
Author-email: Ayllu Academy <Ayllu.Academy@ayllu.io>
Maintainer: Moxie
Maintainer-email: Giancarlo P <gpablo@ayllu.io>
License: MIT License        
Project-URL: Homepage, http://ayllu.io/
Project-URL: GitHub, https://github.com/AylluAcademy-org
Keywords: iot,ayllu
Classifier: Programming Language :: Python :: 3
Classifier: License :: OSI Approved :: MIT License
Classifier: Operating System :: OS Independent
Requires-Python: >=3.7
License-File: LICENSE
Requires-Dist: python-dotenv (==0.20.0)
Provides-Extra: aws
Requires-Dist: awscrt (==0.13.11) ; extra == 'aws'
Requires-Dist: awsiotsdk (==1.11.2) ; extra == 'aws'
